{"mc": {"action": {"frameRate":12,"Big_AttackEndTime":"0","events":[],"frames":[{"res":"stand20001","x":"-134","y":"-242"},{"res":"stand20002","x":"-136","y":"-234"},{"res":"stand20003","x":"-137","y":"-233"},{"res":"stand20004","x":"-131","y":"-247"},{"res":"stand20005","x":"-125","y":"-263"},{"res":"stand20006","x":"-129","y":"-275"},{"res":"stand20007","x":"-133","y":"-271"},{"res":"stand20008","x":"-135","y":"-254"}]}},"res":{"stand20001":{"x":247,"y":1,"w":254,"h":254},"stand20002":{"x":729,"y":1,"w":255,"h":246},"stand20003":{"x":247,"y":257,"w":247,"h":244},"stand20004":{"x":1,"y":270,"w":229,"h":259},"stand20005":{"x":496,"y":286,"w":213,"h":276},"stand20006":{"x":729,"y":249,"w":213,"h":288},"stand20007":{"x":503,"y":1,"w":224,"h":283},"stand20008":{"x":1,"y":1,"w":244,"h":267}}}